README.md
setup.py
my_pq/__init__.py
my_pq/ivfpq.py
my_pq/pq.py
my_pq.egg-info/PKG-INFO
my_pq.egg-info/SOURCES.txt
my_pq.egg-info/dependency_links.txt
my_pq.egg-info/top_level.txt