Metadata-Version: 2.1
Name: my-pq
Version: 0.0.2
Summary: just for fun
Home-page: https://github.com/hzfei/my_pq
Author: hzfei
Author-email: 1027551108@qq.com
License: UNKNOWN
Platform: UNKNOWN
Classifier: Programming Language :: Python :: 3
Classifier: License :: OSI Approved :: MIT License
Classifier: Operating System :: OS Independent
